Group_1/Cluster.py
Group_1/__init__.py
Group_1/utils.py
Group_1-0.0.3.dist-info/LICENSE
Group_1-0.0.3.dist-info/METADATA
Group_1-0.0.3.dist-info/WHEEL
Group_1-0.0.3.dist-info/top_level.txt
Group_1-0.0.3.dist-info/RECORD
