Metadata-Version: 2.1
Name: Group-1
Version: 0.0.3
Summary: A package for clustering
Home-page: https://cseegit.essex.ac.uk/2020_ce903/ce903_team01/
Author: Varun Dutt
Author-email: varun9213@gmail.com
License: UNKNOWN
Platform: UNKNOWN
Classifier: Programming Language :: Python :: 3.7
Classifier: License :: OSI Approved :: GNU General Public License v3 (GPLv3)
Requires-Dist: ipython (>=6)
Requires-Dist: nbformat (>=4)
Requires-Dist: nbconvert (>=5)
Requires-Dist: requests (>=2)
